<?xml version="1.0" ?>
<updates>
	<update>
		<name>EnvironmentDetect 2.0.0</name>
		<description>EnvironmentDetect Plugin</description>
		<element>environmentdetect</element>
		<type>plugin</type>
		<folder>system</folder>
		<client>site</client>
		<version>2.0.0</version>
		<infourl title="EnvironmentDetect Plugin">https://github.com/zero-24/plg_system_environmentdetect</infourl>
		<downloads>
			<downloadurl type="full" format="zip">https://github.com/zero-24/plg_system_environmentdetect/releases/download/2.0.0/plg_system_environmentdetect.zip</downloadurl>
		</downloads>
		<sha512>5f7ad27a4748887be7ee9f32533822f80f893730991a5f9c0455dfdd6f6d3134358fc368a0a239a1b576b844fdd20c659114aab7b2045a9ba0ea8be968ac400a</sha512>
		<tags>
			<tag>stable</tag>
		</tags>
		<maintainer>Tobias Zulauf</maintainer>
		<maintainerurl>https://www.jah-tz.de</maintainerurl>
		<php_minimum>7.2.5</php_minimum>
		<targetplatform name="joomla" version="3.10"/>
	</update>
	<update>
		<name>EnvironmentDetect 2.0.0</name>
		<description>EnvironmentDetect Plugin</description>
		<element>environmentdetect</element>
		<type>plugin</type>
		<folder>system</folder>
		<client>site</client>
		<version>2.0.0</version>
		<infourl title="EnvironmentDetect Plugin">https://github.com/zero-24/plg_system_environmentdetect</infourl>
		<downloads>
			<downloadurl type="full" format="zip">https://github.com/zero-24/plg_system_environmentdetect/releases/download/2.0.0/plg_system_environmentdetect.zip</downloadurl>
		</downloads>
		<sha512>5f7ad27a4748887be7ee9f32533822f80f893730991a5f9c0455dfdd6f6d3134358fc368a0a239a1b576b844fdd20c659114aab7b2045a9ba0ea8be968ac400a</sha512>
		<tags>
			<tag>stable</tag>
		</tags>
		<maintainer>Tobias Zulauf</maintainer>
		<maintainerurl>https://www.jah-tz.de</maintainerurl>
		<php_minimum>7.2.5</php_minimum>
		<targetplatform name="joomla" version="4.0"/>
	</update>
</updates>
